topsis/__init__.py
topsis/topsis.py
Topsis_Rijul_102217207-1.0.0.dist-info/LICENSE.txt
Topsis_Rijul_102217207-1.0.0.dist-info/METADATA
Topsis_Rijul_102217207-1.0.0.dist-info/WHEEL
Topsis_Rijul_102217207-1.0.0.dist-info/top_level.txt
Topsis_Rijul_102217207-1.0.0.dist-info/RECORD
