Metadata-Version: 2.1
Name: Topsis-Rijul-102217207
Version: 1.0.0
Summary: A Python package for implementing the TOPSIS decision-making method
Home-page: UNKNOWN
Author: Rijul Bansal
Author-email: your-email@example.com
License: UNKNOWN
Platform: UNKNOWN
Classifier: Programming Language :: Python :: 3
Classifier: License :: OSI Approved :: MIT License
Classifier: Operating System :: OS Independent
Requires-Python: >=3.6
Requires-Dist: pandas>=1.1.0
Requires-Dist: numpy>=1.19.0
